mozconfigwrapper/__init__.py
mozconfigwrapper/mozconfig.py
mozconfigwrapper/template
mozconfigwrapper-1.0.0.data/scripts/mozconfigwrapper.sh
mozconfigwrapper-1.0.0.dist-info/METADATA
mozconfigwrapper-1.0.0.dist-info/WHEEL
mozconfigwrapper-1.0.0.dist-info/entry_points.txt
mozconfigwrapper-1.0.0.dist-info/top_level.txt
mozconfigwrapper-1.0.0.dist-info/RECORD
