Metadata-Version: 2.1
Name: mozconfigwrapper
Version: 1.0.0
Summary: Utility to make working with mozconfigs easier
Home-page: http://github.com/ahal/mozconfigwrapper
Author: Andrew Halberstadt
Author-email: ahal@pm.me
License: MPL 2.0/GPL 2.0/LGPL 2.1
Platform: Unix
Classifier: Development Status :: 5 - Production/Stable
Classifier: Environment :: Console
Classifier: Intended Audience :: Developers
Classifier: License :: OSI Approved :: Mozilla Public License 2.0 (MPL 2.0)
Classifier: Operating System :: POSIX
Classifier: Programming Language :: Python :: 3
Classifier: Topic :: Software Development :: Libraries :: Python Modules
Requires-Python: >=3.5
